log_events/__init__.py
log_events/log_events.py
log_events-0.1.0.dist-info/METADATA
log_events-0.1.0.dist-info/WHEEL
log_events-0.1.0.dist-info/RECORD
