Metadata-Version: 2.1
Name: log_events
Version: 0.1.0
Summary: A util to log events
Author: Ashritha Shankar
Author-email: ashritha.shankar@solitontech.com
Requires-Python: >=3.12,<4.0
Classifier: Programming Language :: Python :: 3
Classifier: Programming Language :: Python :: 3.12
